osutil.py
osutil-0.0.10.dist-info/LICENSE
osutil-0.0.10.dist-info/METADATA
osutil-0.0.10.dist-info/WHEEL
osutil-0.0.10.dist-info/top_level.txt
osutil-0.0.10.dist-info/RECORD
